deflatable/__init__.py
deflatable/__main__.py
deflatable/app.py
deflatable/config.py
deflatable/display.py
deflatable/schema.py
deflatable/screens.py
deflatable/state.py
deflatable/validate.py
deflatable-0.1.0.dist-info/METADATA
deflatable-0.1.0.dist-info/WHEEL
deflatable-0.1.0.dist-info/entry_points.txt
deflatable-0.1.0.dist-info/licenses/LICENSE
deflatable-0.1.0.dist-info/RECORD
