Metadata-Version: 2.4
Name: deflatable
Version: 0.1.0
Summary: A no-code TUI for browsing SQLite databases
Project-URL: Homepage, https://github.com/ryanlovett/deflatable
Project-URL: Repository, https://github.com/ryanlovett/deflatable
Project-URL: Issues, https://github.com/ryanlovett/deflatable/issues
Author-email: Ryan Lovett <rylo@berkeley.edu>
License: BSD-3-Clause
License-File: LICENSE
Keywords: browser,database,sqlite,tui
Classifier: Development Status :: 4 - Beta
Classifier: Environment :: Console
Classifier: Intended Audience :: Developers
Classifier: License :: OSI Approved :: BSD License
Classifier: Programming Language :: Python :: 3
Classifier: Programming Language :: Python :: 3.10
Classifier: Programming Language :: Python :: 3.11
Classifier: Programming Language :: Python :: 3.12
Classifier: Topic :: Database
Classifier: Topic :: Utilities
Requires-Python: >=3.10
Requires-Dist: rich>=13.0.0
Requires-Dist: textual>=0.47.0
Provides-Extra: dev
Requires-Dist: pre-commit>=3.0.0; extra == 'dev'
Requires-Dist: pytest-asyncio>=0.21.0; extra == 'dev'
Requires-Dist: pytest>=7.0.0; extra == 'dev'
Requires-Dist: ruff>=0.6.0; extra == 'dev'
